lpr_pkg/__init__.py
lpr_pkg/helpers.py
lpr_pkg/model_class.py
lpr_pkg/utils.py
lpr_pkg-3.0.4.dist-info/METADATA
lpr_pkg-3.0.4.dist-info/WHEEL
lpr_pkg-3.0.4.dist-info/RECORD
