Metadata-Version: 2.1
Name: lpr-pkg
Version: 3.0.4
Summary: 
Author: Your Name
Author-email: you@example.com
Requires-Python: >=3.8,<3.12
Classifier: Programming Language :: Python :: 3
Classifier: Programming Language :: Python :: 3.8
Classifier: Programming Language :: Python :: 3.9
Classifier: Programming Language :: Python :: 3.10
Classifier: Programming Language :: Python :: 3.11
Requires-Dist: easydict (==1.9)
Requires-Dist: joblib (>=1.2.0,<2.0.0)
Requires-Dist: numpy (==1.23.5)
Requires-Dist: onnxruntime (==1.11.1)
Requires-Dist: opencv-python (==4.6.0.66)
Requires-Dist: python-levenshtein (==0.20.9)
Requires-Dist: tensorflow (==2.11.0)
Requires-Dist: tritonclient[grpc] (>=2.33.0,<3.0.0)
